ansible_tower_mcp/__init__.py
ansible_tower_mcp/main.py
iflow_mcp_a37ai_ansible_tower_mcp-0.1.0.dist-info/METADATA
iflow_mcp_a37ai_ansible_tower_mcp-0.1.0.dist-info/WHEEL
iflow_mcp_a37ai_ansible_tower_mcp-0.1.0.dist-info/entry_points.txt
iflow_mcp_a37ai_ansible_tower_mcp-0.1.0.dist-info/licenses/LICENSE
iflow_mcp_a37ai_ansible_tower_mcp-0.1.0.dist-info/RECORD
