Metadata-Version: 2.4
Name: iflow-mcp_a37ai_ansible-tower-mcp
Version: 0.1.0
Summary: An MCP Server so that LLMs can interact with Ansible Tower
License-File: LICENSE
Requires-Python: >=3.8
Requires-Dist: fastmcp
Requires-Dist: requests
